README.md
setup.py
PyFRS/__init__.py
PyFRS/astro.py
PyFRS/cgs.py
PyFRS/cosmocalc.py
PyFRS/fs.py
PyFRS/grb.py
PyFRS/rs.py
PyFRS/rs_scaling.py
PyFRS.egg-info/PKG-INFO
PyFRS.egg-info/SOURCES.txt
PyFRS.egg-info/dependency_links.txt
PyFRS.egg-info/top_level.txt
test/test.py
test/test01.py