Metadata-Version: 2.1
Name: PyFRS
Version: 0.0.9
Summary: Compute the multiband emissions from Forward-Reverse Shocks of a GRB or TDE jet
Author: Wei-Hua Lei
Author-email: leiwh78@gmail.com
